{
  "schema_version": "deutsch_web_lesson_v1",
  "lesson_id": "1.127",
  "aufgabe": "1.127",
  "modul": "Hören",
  "niveau": "B1",
  "teil": 1,
  "source_book": "deutsch-vorbereitung",
  "thema": "Heute Nachmittag zum Hauptbahnhof",
  "title": "Heute Nachmittag zum Hauptbahnhof",
  "instructions": "Sie hören kurze Texte. Zu jedem Text gibt es eine Aufgabe. Kreuzen Sie die richtige Antwort an.",
  "source": {
    "origin_url": "https://deutsch-vorbereitung.com/en/uebung-312.html",
    "lingq_lesson_id": null,
    "lingq_course_id": null,
    "lingq_reader_url": null
  },
  "audio": {
    "url": null,
    "host": "none",
    "local_path": "input/html/deutsch-vorbereitung/horen/1.127/1.127.mp3"
  },
  "aussagen": [
    {
      "id": "1.127-1",
      "label": "Wie kann man heute Nachmittag zum Hauptbahnhof kommen?",
      "correct": "a",
      "options": [
        {
          "key": "a",
          "text": "Mit der U-oder S-Bahn."
        },
        {
          "key": "b",
          "text": "Mit dem Auto."
        },
        {
          "key": "c",
          "text": "Mit der Straßenbahn oder dem Bus."
        }
      ]
    }
  ],
  "transcript": [
    {
      "label": "Transkription",
      "text": "Wir unterbrechen unser Programm für eine wichtige Mitteilung. Ein schwerer Verkehrsunfall führt dazu, dass der Bereich in den Hauptbahnhof bis zum Abend für den gesamten Autoverkehr gesperrt ist. Ebenso wird der öffentliche Nahverkehr in Form von Straßenbahnen und Bussen nicht bis zum Hauptbahnhof gefahren. Wenn Sie dennoch den Bahnhof erreichen müssen, wird empfohlen, stattdessen auf die U-Bahn und S-Bahn auszuweichen.",
      "key_phrase": ""
    }
  ],
  "vocab": [],
  "_meta": {
    "note_vocab_id": "null = chưa link vocab_master. Vai Vocab Extractor / deutsch_web_sync điền sau khi match wort trong data/03_unified/vocab_master.csv. KHÔNG bịa ID.",
    "note_lv": "lv = trạng thái panel (new/ok/hard) ánh xạ lv-new/lv-ok/lv-hard trong drill.css.",
    "generated_by": "horen_to_lesson_json.py Phase B 2026-05-31"
  }
}
