{
  "schema_version": "deutsch_web_lesson_v1",
  "lesson_id": "1.37",
  "aufgabe": "1.37",
  "modul": "Hören",
  "niveau": "B1",
  "teil": 1,
  "source_book": "deutsch-vorbereitung",
  "thema": "Anwaltskanzlei",
  "title": "Anwaltskanzlei",
  "instructions": "Sie hören kurze Texte. Zu jedem Text gibt es eine Aufgabe. Kreuzen Sie die richtige Antwort an.",
  "source": {
    "origin_url": "https://deutsch-vorbereitung.com/en/uebung-1987.html",
    "lingq_lesson_id": 44848984,
    "lingq_course_id": 2747707,
    "lingq_reader_url": "https://www.lingq.com/en/learn/de/web/reader/44848984/"
  },
  "audio": {
    "url": "https://s3.amazonaws.com/media.lingq.com/resources/contents/audio/1.37.6b1f617b55f.mp3",
    "host": "lingq_s3",
    "local_path": "input/html/deutsch-vorbereitung/horen/1.37/1.37.mp3"
  },
  "aussagen": [
    {
      "id": "1.37-1",
      "label": "Warum soll die Person Frau Schmidt zurückrufen?",
      "correct": "b",
      "options": [
        {
          "key": "a",
          "text": "Um einen Termin zu vereinbaren."
        },
        {
          "key": "b",
          "text": "Um wichtige Neuigkeiten zu erfahren."
        },
        {
          "key": "c",
          "text": "Um eine Rechnung zu begleichen."
        }
      ]
    }
  ],
  "transcript": [
    {
      "label": "Transkription",
      "text": "Hallo, hier ist Frau Schmidt von der Anwaltskanzlei. Bitte rufen Sie mich dringend zurück, es gibt wichtige Neuigkeiten in Ihrer aktuellen Rechtsangelegenheit. Meine Rückrufnummer lautet 030 123 456789, um einen Termin zu vereinbaren. Vielen Dank, dass Sie Ihre aktuelle Rechnung pünktlich bezahlt haben.",
      "key_phrase": ""
    }
  ],
  "vocab": [],
  "_meta": {
    "note_vocab_id": "null = chưa link vocab_master. Vai Vocab Extractor / deutsch_web_sync điền sau khi match wort trong data/03_unified/vocab_master.csv. KHÔNG bịa ID.",
    "note_lv": "lv = trạng thái panel (new/ok/hard) ánh xạ lv-new/lv-ok/lv-hard trong drill.css.",
    "generated_by": "horen_to_lesson_json.py Phase B 2026-05-31"
  }
}
